bighummingbird/__init__.py
bighummingbird/dataset.py
bighummingbird/judge.py
bighummingbird/apis/__init__.py
bighummingbird/apis/project.py
bighummingbird/apis/workspace.py
bighummingbird/utils/__init__.py
bighummingbird/utils/constants.py
bighummingbird/utils/display_util.py
bighummingbird/utils/entity.py
bighummingbird/utils/error_handling.py
bighummingbird/utils/file.py
bighummingbird/utils/source_code.py
bighummingbird-0.0.2024072501.dist-info/METADATA
bighummingbird-0.0.2024072501.dist-info/WHEEL
bighummingbird-0.0.2024072501.dist-info/top_level.txt
bighummingbird-0.0.2024072501.dist-info/RECORD
