Metadata-Version: 2.1
Name: bighummingbird
Version: 0.0.2024072501
Summary: bighummingbird
Keywords: python,first package
Classifier: Development Status :: 3 - Alpha
Classifier: Intended Audience :: Education
Classifier: Programming Language :: Python :: 2
Classifier: Programming Language :: Python :: 3
Classifier: Operating System :: MacOS :: MacOS X
Classifier: Operating System :: Microsoft :: Windows
Requires-Dist: pip ==24.1.1
Requires-Dist: certifi ==2024.7.4
Requires-Dist: charset-normalizer ==3.3.2
Requires-Dist: idna ==3.7
Requires-Dist: python-dotenv ==1.0.1
Requires-Dist: requests ==2.31.0
Requires-Dist: urllib3 ==2.2.2
